setup.py
nlp_model_flow/__init__.py
nlp_model_flow/model_flow.py
nlp_model_flow/nlp_analysis.py
nlp_model_flow.egg-info/PKG-INFO
nlp_model_flow.egg-info/SOURCES.txt
nlp_model_flow.egg-info/dependency_links.txt
nlp_model_flow.egg-info/not-zip-safe
nlp_model_flow.egg-info/top_level.txt