Metadata-Version: 1.0
Name: nlp-model-flow
Version: 0.1
Summary: workCloud analysis and linear model activation
Home-page: UNKNOWN
Author: UNKNOWN
Author-email: UNKNOWN
License: UNKNOWN
Platform: UNKNOWN
